{
    "imported_rules": {
        "": {
            "function": {
                "main/create_environment": "begin\nobligation(acknowledge source, [source], stage = \"import\").\nattribute( source, [\"str\" \"UoE\"]).\nend",
                "main/create_environment_2": "begin\nobligation( acknowledge source, [source], stage = \"import\").\nattribute(source, [\"str\" \"UoE\"]).\nend",
                "main/create_environment_3": "begin\nobligation( acknowledge source, [source], stage = \"import\").\nattribute(source, [\"str\" \"UoE\"]).\nend"
            }
        }
    },
    "flow_rules": {
        "": {
            "function": {
                "main/processfiles_2": "\"cyclone_workflow\" -> \"output'\"\ndelete(*, *, *, *, \"UoE\")\n",
                "main/processfiles_3": "\"cyclone_workflow\" -> \"output\"\nedit(*, *, *, *, \"UoE\", \"str\", \"UK\")\n"
            }
        }
    }
}
